mcp_youtube_transcript/__init__.py
mcp_youtube_transcript/__main__.py
mcp_youtube_transcript/cli.py
mcp_youtube_transcript-0.3.5.dist-info/METADATA
mcp_youtube_transcript-0.3.5.dist-info/WHEEL
mcp_youtube_transcript-0.3.5.dist-info/entry_points.txt
mcp_youtube_transcript-0.3.5.dist-info/licenses/LICENSE
mcp_youtube_transcript-0.3.5.dist-info/RECORD
