Metadata-Version: 2.4
Name: mcp-youtube-transcript
Version: 0.3.5
Summary: MCP server retrieving transcripts of YouTube videos
Author-email: Junpei Kawamoto <kawamoto.junpei@gmail.com>
License-File: LICENSE
Classifier: Development Status :: 4 - Beta
Classifier: License :: OSI Approved :: MIT License
Classifier: Programming Language :: Python :: 3 :: Only
Classifier: Programming Language :: Python :: 3.10
Classifier: Programming Language :: Python :: 3.11
Classifier: Programming Language :: Python :: 3.12
Classifier: Programming Language :: Python :: 3.13
Requires-Python: >=3.10
Requires-Dist: beautifulsoup4>=4.13.3
Requires-Dist: click>=8.1.8
Requires-Dist: mcp>=1.9
Requires-Dist: pydantic>=2.10.6
Requires-Dist: requests>=2.32.3
Requires-Dist: rich-click>=1.8.8
Requires-Dist: youtube-transcript-api>=1.1
